datetypes-0.1.0.dist-info/METADATA
datetypes-0.1.0.dist-info/WHEEL
datetypes-0.1.0.dist-info/entry_points.txt
datetypes/__init__.py
datetypes/__init__.pyi
datetypes/py.typed
datetypes-0.1.0.dist-info/RECORD
