Metadata-Version: 2.1
Name: datetypes
Version: 0.1.0
Summary: Typed counterparts for built-in `datetime` module classes
Author-Email: Matteo Bernardini <matteo@teobe.net>
License: MIT
Classifier: Development Status :: 4 - Beta
Classifier: Intended Audience :: Developers
Classifier: Typing :: Typed
Classifier: Topic :: System
Classifier: Topic :: Utilities
Classifier: Topic :: Software Development :: Localization
Classifier: Topic :: Software Development :: Libraries :: Python Modules
Classifier: Programming Language :: Python :: 3.13
Classifier: Programming Language :: Python :: 3.12
Classifier: Programming Language :: Python :: 3.11
Classifier: Programming Language :: Python :: 3.10
Classifier: Programming Language :: Python :: 3.9
Requires-Python: >=3.9
